krinn/__init__.py
krinn/amazon.py
krinn-0.0.1.dist-info/LICENSE
krinn-0.0.1.dist-info/METADATA
krinn-0.0.1.dist-info/WHEEL
krinn-0.0.1.dist-info/top_level.txt
krinn-0.0.1.dist-info/RECORD
