Metadata-Version: 2.1
Name: krinn
Version: 0.0.1
Summary: This module helps in getting the price or title of a product
Home-page: https://github.com/BRAINIFII/krinn
Author: Kritik Bangera
Author-email: bangerakritik@gmail.com
License: UNKNOWN
Platform: UNKNOWN
Classifier: Programming Language :: Python :: 3
Classifier: License :: OSI Approved :: MIT License
Classifier: Operating System :: OS Independent
Requires-Python: >=3.6
Requires-Dist: bs4
Requires-Dist: requests
Requires-Dist: user-agents
Provides-Extra: devlp
Requires-Dist: pytest (>=3.7) ; extra == 'devlp'
